sila2_toolkit/silaspoofer/__init__.py
sila2_toolkit/silaspoofer/__main__.py
sila2_toolkit/silaspoofer/silaspoofer.py
sila2_toolkit-3.dist-info/LICENSE
sila2_toolkit-3.dist-info/METADATA
sila2_toolkit-3.dist-info/WHEEL
sila2_toolkit-3.dist-info/top_level.txt
sila2_toolkit-3.dist-info/RECORD
