Metadata-Version: 2.1
Name: sila2-toolkit
Version: 3
Summary: Various sila2 helper functions.
Author-email: Mette Gere <umge@novonordisk.com>
Classifier: Programming Language :: Python :: 3
Classifier: License :: OSI Approved :: MIT License
Classifier: Operating System :: OS Independent
Requires-Python: >=3.7
License-File: LICENSE
Requires-Dist: click
Requires-Dist: sila2
Provides-Extra: dev
Requires-Dist: black ==23.9.1 ; extra == 'dev'
Requires-Dist: bumpver ; extra == 'dev'
Requires-Dist: isort ; extra == 'dev'
Requires-Dist: build ==0.10.0 ; extra == 'dev'
